docker_tags_getter/__init__.py
docker_tags_getter/api/__init__.py
docker_tags_getter/api/v2/__init__.py
docker_tags_getter/api/v2/repositories_api.py
docker_tags_getter/api/v2/tags_api.py
docker_tags_getter/cli/cli.py
docker_tags_getter/cli/repo.py
docker_tags_getter/cli/repos.py
docker_tags_getter/config/__init__.py
docker_tags_getter/config/headers_config.py
docker_tags_getter/fetcher/__init__.py
docker_tags_getter/fetcher/api_fetcher.py
docker_tags_getter/filters/__init__.py
docker_tags_getter/filters/tags_filter.py
docker_tags_getter/main.py
docker_tags_getter-0.3.5.dist-info/COPYING
docker_tags_getter-0.3.5.dist-info/COPYING.LESSER
docker_tags_getter-0.3.5.dist-info/WHEEL
docker_tags_getter-0.3.5.dist-info/METADATA
docker_tags_getter-0.3.5.dist-info/entry_points.txt
docker_tags_getter-0.3.5.dist-info/RECORD
